perspective_transformer/__init__.py
perspective_transformer/main.py
perspective_transformer-1.0.3.dist-info/LICENSE
perspective_transformer-1.0.3.dist-info/METADATA
perspective_transformer-1.0.3.dist-info/WHEEL
perspective_transformer-1.0.3.dist-info/entry_points.txt
perspective_transformer-1.0.3.dist-info/top_level.txt
perspective_transformer-1.0.3.dist-info/RECORD
