Metadata-Version: 2.1
Name: perspective-transformer
Version: 1.0.3
Summary: A GUI tool to apply perspective transformations to images.
Author-email: Jiucheng Zang <zangjiucheng@gmail.com>
License: MIT
Project-URL: homepage, https://github.com/zangjiucheng/Perspective-Transformer
Project-URL: repository, https://github.com/zangjiucheng/Perspective-Transformer
Requires-Python: >=3.7
License-File: LICENSE
Requires-Dist: PySide6
Requires-Dist: opencv-python-headless
Requires-Dist: numpy
